[{"arguments":["clang","-Wno-documentation-unknown-command","-Wno-unknown-warning-option","-Wno-unknown-pragmas","-nostdinc","-nostdinc++","-DQT_QML_DEBUG","-g","-std=gnu++17","-fdiagnostics-color=always","-fsyntax-only","-m64","--target=x86_64-w64-mingw32","-DMINGW_HAS_SECURE_API","-DQT_CORE_LIB","-DQT_GUI_LIB","-DQT_NEEDS_QMAIN","-DQT_WIDGETS_LIB","-DUNICODE","-DWIN32","-DWIN64","-D_ENABLE_EXTENDED_ALIGNED_STORAGE","-D_UNICODE","-D_WIN64","-DQ_CREATOR_RUN","-DQT_ANNOTATE_FUNCTION(x)=__attribute__((annotate(#x)))","-IE:\\qt\\Tools\\QtCreator\\share\\qtcreator\\cplusplus\\wrappedMingwHeaders","-IE:\\qt\\Tools\\QtCreator\\share\\qtcreator\\cplusplus\\wrappedQtHeaders","-IE:\\qt\\Tools\\QtCreator\\share\\qtcreator\\cplusplus\\wrappedQtHeaders\\QtCore","-IC:\\Users\\16645\\Desktop\\McDonald\\build\\Desktop_Qt_6_7_0_MinGW_64_bit-Debug\\McDonald_autogen\\include","-IE:\\qt\\6.7.0\\mingw_64\\include\\QtCore","-IE:\\qt\\6.7.0\\mingw_64\\include","-IE:\\qt\\6.7.0\\mingw_64\\mkspecs\\win32-g++","-IE:\\qt\\6.7.0\\mingw_64\\include\\QtWidgets","-IE:\\qt\\6.7.0\\mingw_64\\include\\QtGui","-isystem","E:\\qt\\Tools\\mingw1120_64\\lib\\gcc\\x86_64-w64-mingw32\\11.2.0\\include\\c++","-isystem","E:\\qt\\Tools\\mingw1120_64\\lib\\gcc\\x86_64-w64-mingw32\\11.2.0\\include\\c++\\x86_64-w64-mingw32","-isystem","E:\\qt\\Tools\\mingw1120_64\\lib\\gcc\\x86_64-w64-mingw32\\11.2.0\\include\\c++\\backward","-isystem","E:\\qt\\Tools\\QtCreator\\bin\\clang\\lib\\clang\\17\\include","-isystem","E:\\qt\\Tools\\mingw1120_64\\x86_64-w64-mingw32\\include","-fmessage-length=0","-fdiagnostics-show-note-include-stack","-fretain-comments-from-system-headers","-fmacro-backtrace-limit=0","-ferror-limit=1000","-x","c++","C:\\Users\\16645\\Desktop\\McDonald\\main.cpp"],"directory":"C:/Users/16645/Desktop/McDonald/build/Desktop_Qt_6_7_0_MinGW_64_bit-Debug/.qtc_clangd","file":"C:/Users/16645/Desktop/McDonald/main.cpp"},{"arguments":["clang","-Wno-documentation-unknown-command","-Wno-unknown-warning-option","-Wno-unknown-pragmas","-nostdinc","-nostdinc++","-DQT_QML_DEBUG","-g","-std=gnu++17","-fdiagnostics-color=always","-fsyntax-only","-m64","--target=x86_64-w64-mingw32","-DMINGW_HAS_SECURE_API","-DQT_CORE_LIB","-DQT_GUI_LIB","-DQT_NEEDS_QMAIN","-DQT_WIDGETS_LIB","-DUNICODE","-DWIN32","-DWIN64","-D_ENABLE_EXTENDED_ALIGNED_STORAGE","-D_UNICODE","-D_WIN64","-DQ_CREATOR_RUN","-DQT_ANNOTATE_FUNCTION(x)=__attribute__((annotate(#x)))","-IE:\\qt\\Tools\\QtCreator\\share\\qtcreator\\cplusplus\\wrappedMingwHeaders","-IE:\\qt\\Tools\\QtCreator\\share\\qtcreator\\cplusplus\\wrappedQtHeaders","-IE:\\qt\\Tools\\QtCreator\\share\\qtcreator\\cplusplus\\wrappedQtHeaders\\QtCore","-IC:\\Users\\16645\\Desktop\\McDonald\\build\\Desktop_Qt_6_7_0_MinGW_64_bit-Debug\\McDonald_autogen\\include","-IE:\\qt\\6.7.0\\mingw_64\\include\\QtCore","-IE:\\qt\\6.7.0\\mingw_64\\include","-IE:\\qt\\6.7.0\\mingw_64\\mkspecs\\win32-g++","-IE:\\qt\\6.7.0\\mingw_64\\include\\QtWidgets","-IE:\\qt\\6.7.0\\mingw_64\\include\\QtGui","-isystem","E:\\qt\\Tools\\mingw1120_64\\lib\\gcc\\x86_64-w64-mingw32\\11.2.0\\include\\c++","-isystem","E:\\qt\\Tools\\mingw1120_64\\lib\\gcc\\x86_64-w64-mingw32\\11.2.0\\include\\c++\\x86_64-w64-mingw32","-isystem","E:\\qt\\Tools\\mingw1120_64\\lib\\gcc\\x86_64-w64-mingw32\\11.2.0\\include\\c++\\backward","-isystem","E:\\qt\\Tools\\QtCreator\\bin\\clang\\lib\\clang\\17\\include","-isystem","E:\\qt\\Tools\\mingw1120_64\\x86_64-w64-mingw32\\include","-fmessage-length=0","-fdiagnostics-show-note-include-stack","-fretain-comments-from-system-headers","-fmacro-backtrace-limit=0","-ferror-limit=1000","-x","c++","C:\\Users\\16645\\Desktop\\McDonald\\mainwindow.cpp"],"directory":"C:/Users/16645/Desktop/McDonald/build/Desktop_Qt_6_7_0_MinGW_64_bit-Debug/.qtc_clangd","file":"C:/Users/16645/Desktop/McDonald/mainwindow.cpp"},{"arguments":["clang","-Wno-documentation-unknown-command","-Wno-unknown-warning-option","-Wno-unknown-pragmas","-nostdinc","-nostdinc++","-DQT_QML_DEBUG","-g","-std=gnu++17","-fdiagnostics-color=always","-fsyntax-only","-m64","--target=x86_64-w64-mingw32","-DMINGW_HAS_SECURE_API","-DQT_CORE_LIB","-DQT_GUI_LIB","-DQT_NEEDS_QMAIN","-DQT_WIDGETS_LIB","-DUNICODE","-DWIN32","-DWIN64","-D_ENABLE_EXTENDED_ALIGNED_STORAGE","-D_UNICODE","-D_WIN64","-DQ_CREATOR_RUN","-DQT_ANNOTATE_FUNCTION(x)=__attribute__((annotate(#x)))","-IE:\\qt\\Tools\\QtCreator\\share\\qtcreator\\cplusplus\\wrappedMingwHeaders","-IE:\\qt\\Tools\\QtCreator\\share\\qtcreator\\cplusplus\\wrappedQtHeaders","-IE:\\qt\\Tools\\QtCreator\\share\\qtcreator\\cplusplus\\wrappedQtHeaders\\QtCore","-IC:\\Users\\16645\\Desktop\\McDonald\\build\\Desktop_Qt_6_7_0_MinGW_64_bit-Debug\\McDonald_autogen\\include","-IE:\\qt\\6.7.0\\mingw_64\\include\\QtCore","-IE:\\qt\\6.7.0\\mingw_64\\include","-IE:\\qt\\6.7.0\\mingw_64\\mkspecs\\win32-g++","-IE:\\qt\\6.7.0\\mingw_64\\include\\QtWidgets","-IE:\\qt\\6.7.0\\mingw_64\\include\\QtGui","-isystem","E:\\qt\\Tools\\mingw1120_64\\lib\\gcc\\x86_64-w64-mingw32\\11.2.0\\include\\c++","-isystem","E:\\qt\\Tools\\mingw1120_64\\lib\\gcc\\x86_64-w64-mingw32\\11.2.0\\include\\c++\\x86_64-w64-mingw32","-isystem","E:\\qt\\Tools\\mingw1120_64\\lib\\gcc\\x86_64-w64-mingw32\\11.2.0\\include\\c++\\backward","-isystem","E:\\qt\\Tools\\QtCreator\\bin\\clang\\lib\\clang\\17\\include","-isystem","E:\\qt\\Tools\\mingw1120_64\\x86_64-w64-mingw32\\include","-fmessage-length=0","-fdiagnostics-show-note-include-stack","-fretain-comments-from-system-headers","-fmacro-backtrace-limit=0","-ferror-limit=1000","-x","c++","C:\\Users\\16645\\Desktop\\McDonald\\input.cpp"],"directory":"C:/Users/16645/Desktop/McDonald/build/Desktop_Qt_6_7_0_MinGW_64_bit-Debug/.qtc_clangd","file":"C:/Users/16645/Desktop/McDonald/input.cpp"},{"arguments":["clang","-Wno-documentation-unknown-command","-Wno-unknown-warning-option","-Wno-unknown-pragmas","-nostdinc","-nostdinc++","-DQT_QML_DEBUG","-g","-std=gnu++17","-fdiagnostics-color=always","-fsyntax-only","-m64","--target=x86_64-w64-mingw32","-DMINGW_HAS_SECURE_API","-DQT_CORE_LIB","-DQT_GUI_LIB","-DQT_NEEDS_QMAIN","-DQT_WIDGETS_LIB","-DUNICODE","-DWIN32","-DWIN64","-D_ENABLE_EXTENDED_ALIGNED_STORAGE","-D_UNICODE","-D_WIN64","-DQ_CREATOR_RUN","-DQT_ANNOTATE_FUNCTION(x)=__attribute__((annotate(#x)))","-IE:\\qt\\Tools\\QtCreator\\share\\qtcreator\\cplusplus\\wrappedMingwHeaders","-IE:\\qt\\Tools\\QtCreator\\share\\qtcreator\\cplusplus\\wrappedQtHeaders","-IE:\\qt\\Tools\\QtCreator\\share\\qtcreator\\cplusplus\\wrappedQtHeaders\\QtCore","-IC:\\Users\\16645\\Desktop\\McDonald\\build\\Desktop_Qt_6_7_0_MinGW_64_bit-Debug\\McDonald_autogen\\include","-IE:\\qt\\6.7.0\\mingw_64\\include\\QtCore","-IE:\\qt\\6.7.0\\mingw_64\\include","-IE:\\qt\\6.7.0\\mingw_64\\mkspecs\\win32-g++","-IE:\\qt\\6.7.0\\mingw_64\\include\\QtWidgets","-IE:\\qt\\6.7.0\\mingw_64\\include\\QtGui","-isystem","E:\\qt\\Tools\\mingw1120_64\\lib\\gcc\\x86_64-w64-mingw32\\11.2.0\\include\\c++","-isystem","E:\\qt\\Tools\\mingw1120_64\\lib\\gcc\\x86_64-w64-mingw32\\11.2.0\\include\\c++\\x86_64-w64-mingw32","-isystem","E:\\qt\\Tools\\mingw1120_64\\lib\\gcc\\x86_64-w64-mingw32\\11.2.0\\include\\c++\\backward","-isystem","E:\\qt\\Tools\\QtCreator\\bin\\clang\\lib\\clang\\17\\include","-isystem","E:\\qt\\Tools\\mingw1120_64\\x86_64-w64-mingw32\\include","-fmessage-length=0","-fdiagnostics-show-note-include-stack","-fretain-comments-from-system-headers","-fmacro-backtrace-limit=0","-ferror-limit=1000","-x","c++","C:\\Users\\16645\\Desktop\\McDonald\\work.cpp"],"directory":"C:/Users/16645/Desktop/McDonald/build/Desktop_Qt_6_7_0_MinGW_64_bit-Debug/.qtc_clangd","file":"C:/Users/16645/Desktop/McDonald/work.cpp"},{"arguments":["clang","-Wno-documentation-unknown-command","-Wno-unknown-warning-option","-Wno-unknown-pragmas","-nostdinc","-nostdinc++","-DQT_QML_DEBUG","-g","-std=gnu++17","-fdiagnostics-color=always","-fsyntax-only","-m64","--target=x86_64-w64-mingw32","-DMINGW_HAS_SECURE_API","-DQT_CORE_LIB","-DQT_GUI_LIB","-DQT_NEEDS_QMAIN","-DQT_WIDGETS_LIB","-DUNICODE","-DWIN32","-DWIN64","-D_ENABLE_EXTENDED_ALIGNED_STORAGE","-D_UNICODE","-D_WIN64","-DQ_CREATOR_RUN","-DQT_ANNOTATE_FUNCTION(x)=__attribute__((annotate(#x)))","-IE:\\qt\\Tools\\QtCreator\\share\\qtcreator\\cplusplus\\wrappedMingwHeaders","-IE:\\qt\\Tools\\QtCreator\\share\\qtcreator\\cplusplus\\wrappedQtHeaders","-IE:\\qt\\Tools\\QtCreator\\share\\qtcreator\\cplusplus\\wrappedQtHeaders\\QtCore","-IC:\\Users\\16645\\Desktop\\McDonald\\build\\Desktop_Qt_6_7_0_MinGW_64_bit-Debug\\McDonald_autogen\\include","-IE:\\qt\\6.7.0\\mingw_64\\include\\QtCore","-IE:\\qt\\6.7.0\\mingw_64\\include","-IE:\\qt\\6.7.0\\mingw_64\\mkspecs\\win32-g++","-IE:\\qt\\6.7.0\\mingw_64\\include\\QtWidgets","-IE:\\qt\\6.7.0\\mingw_64\\include\\QtGui","-isystem","E:\\qt\\Tools\\mingw1120_64\\lib\\gcc\\x86_64-w64-mingw32\\11.2.0\\include\\c++","-isystem","E:\\qt\\Tools\\mingw1120_64\\lib\\gcc\\x86_64-w64-mingw32\\11.2.0\\include\\c++\\x86_64-w64-mingw32","-isystem","E:\\qt\\Tools\\mingw1120_64\\lib\\gcc\\x86_64-w64-mingw32\\11.2.0\\include\\c++\\backward","-isystem","E:\\qt\\Tools\\QtCreator\\bin\\clang\\lib\\clang\\17\\include","-isystem","E:\\qt\\Tools\\mingw1120_64\\x86_64-w64-mingw32\\include","-fmessage-length=0","-fdiagnostics-show-note-include-stack","-fretain-comments-from-system-headers","-fmacro-backtrace-limit=0","-ferror-limit=1000","-x","c++","C:\\Users\\16645\\Desktop\\McDonald\\order_window.cpp"],"directory":"C:/Users/16645/Desktop/McDonald/build/Desktop_Qt_6_7_0_MinGW_64_bit-Debug/.qtc_clangd","file":"C:/Users/16645/Desktop/McDonald/order_window.cpp"},{"arguments":["clang","-Wno-documentation-unknown-command","-Wno-unknown-warning-option","-Wno-unknown-pragmas","-nostdinc","-nostdinc++","-DQT_QML_DEBUG","-g","-std=gnu++17","-fdiagnostics-color=always","-fsyntax-only","-m64","--target=x86_64-w64-mingw32","-DMINGW_HAS_SECURE_API","-DQT_CORE_LIB","-DQT_GUI_LIB","-DQT_NEEDS_QMAIN","-DQT_WIDGETS_LIB","-DUNICODE","-DWIN32","-DWIN64","-D_ENABLE_EXTENDED_ALIGNED_STORAGE","-D_UNICODE","-D_WIN64","-DQ_CREATOR_RUN","-DQT_ANNOTATE_FUNCTION(x)=__attribute__((annotate(#x)))","-IE:\\qt\\Tools\\QtCreator\\share\\qtcreator\\cplusplus\\wrappedMingwHeaders","-IE:\\qt\\Tools\\QtCreator\\share\\qtcreator\\cplusplus\\wrappedQtHeaders","-IE:\\qt\\Tools\\QtCreator\\share\\qtcreator\\cplusplus\\wrappedQtHeaders\\QtCore","-IC:\\Users\\16645\\Desktop\\McDonald\\build\\Desktop_Qt_6_7_0_MinGW_64_bit-Debug\\McDonald_autogen\\include","-IE:\\qt\\6.7.0\\mingw_64\\include\\QtCore","-IE:\\qt\\6.7.0\\mingw_64\\include","-IE:\\qt\\6.7.0\\mingw_64\\mkspecs\\win32-g++","-IE:\\qt\\6.7.0\\mingw_64\\include\\QtWidgets","-IE:\\qt\\6.7.0\\mingw_64\\include\\QtGui","-isystem","E:\\qt\\Tools\\mingw1120_64\\lib\\gcc\\x86_64-w64-mingw32\\11.2.0\\include\\c++","-isystem","E:\\qt\\Tools\\mingw1120_64\\lib\\gcc\\x86_64-w64-mingw32\\11.2.0\\include\\c++\\x86_64-w64-mingw32","-isystem","E:\\qt\\Tools\\mingw1120_64\\lib\\gcc\\x86_64-w64-mingw32\\11.2.0\\include\\c++\\backward","-isystem","E:\\qt\\Tools\\QtCreator\\bin\\clang\\lib\\clang\\17\\include","-isystem","E:\\qt\\Tools\\mingw1120_64\\x86_64-w64-mingw32\\include","-fmessage-length=0","-fdiagnostics-show-note-include-stack","-fretain-comments-from-system-headers","-fmacro-backtrace-limit=0","-ferror-limit=1000","-x","c++-header","C:\\Users\\16645\\Desktop\\McDonald\\mainwindow.h"],"directory":"C:/Users/16645/Desktop/McDonald/build/Desktop_Qt_6_7_0_MinGW_64_bit-Debug/.qtc_clangd","file":"C:/Users/16645/Desktop/McDonald/mainwindow.h"},{"arguments":["clang","-Wno-documentation-unknown-command","-Wno-unknown-warning-option","-Wno-unknown-pragmas","-nostdinc","-nostdinc++","-DQT_QML_DEBUG","-g","-std=gnu++17","-fdiagnostics-color=always","-fsyntax-only","-m64","--target=x86_64-w64-mingw32","-DMINGW_HAS_SECURE_API","-DQT_CORE_LIB","-DQT_GUI_LIB","-DQT_NEEDS_QMAIN","-DQT_WIDGETS_LIB","-DUNICODE","-DWIN32","-DWIN64","-D_ENABLE_EXTENDED_ALIGNED_STORAGE","-D_UNICODE","-D_WIN64","-DQ_CREATOR_RUN","-DQT_ANNOTATE_FUNCTION(x)=__attribute__((annotate(#x)))","-IE:\\qt\\Tools\\QtCreator\\share\\qtcreator\\cplusplus\\wrappedMingwHeaders","-IE:\\qt\\Tools\\QtCreator\\share\\qtcreator\\cplusplus\\wrappedQtHeaders","-IE:\\qt\\Tools\\QtCreator\\share\\qtcreator\\cplusplus\\wrappedQtHeaders\\QtCore","-IC:\\Users\\16645\\Desktop\\McDonald\\build\\Desktop_Qt_6_7_0_MinGW_64_bit-Debug\\McDonald_autogen\\include","-IE:\\qt\\6.7.0\\mingw_64\\include\\QtCore","-IE:\\qt\\6.7.0\\mingw_64\\include","-IE:\\qt\\6.7.0\\mingw_64\\mkspecs\\win32-g++","-IE:\\qt\\6.7.0\\mingw_64\\include\\QtWidgets","-IE:\\qt\\6.7.0\\mingw_64\\include\\QtGui","-isystem","E:\\qt\\Tools\\mingw1120_64\\lib\\gcc\\x86_64-w64-mingw32\\11.2.0\\include\\c++","-isystem","E:\\qt\\Tools\\mingw1120_64\\lib\\gcc\\x86_64-w64-mingw32\\11.2.0\\include\\c++\\x86_64-w64-mingw32","-isystem","E:\\qt\\Tools\\mingw1120_64\\lib\\gcc\\x86_64-w64-mingw32\\11.2.0\\include\\c++\\backward","-isystem","E:\\qt\\Tools\\QtCreator\\bin\\clang\\lib\\clang\\17\\include","-isystem","E:\\qt\\Tools\\mingw1120_64\\x86_64-w64-mingw32\\include","-fmessage-length=0","-fdiagnostics-show-note-include-stack","-fretain-comments-from-system-headers","-fmacro-backtrace-limit=0","-ferror-limit=1000","-x","c++-header","C:\\Users\\16645\\Desktop\\McDonald\\Data_Structure.h"],"directory":"C:/Users/16645/Desktop/McDonald/build/Desktop_Qt_6_7_0_MinGW_64_bit-Debug/.qtc_clangd","file":"C:/Users/16645/Desktop/McDonald/Data_Structure.h"},{"arguments":["clang","-Wno-documentation-unknown-command","-Wno-unknown-warning-option","-Wno-unknown-pragmas","-nostdinc","-nostdinc++","-DQT_QML_DEBUG","-g","-std=gnu++17","-fdiagnostics-color=always","-fsyntax-only","-m64","--target=x86_64-w64-mingw32","-DMINGW_HAS_SECURE_API","-DQT_CORE_LIB","-DQT_GUI_LIB","-DQT_NEEDS_QMAIN","-DQT_WIDGETS_LIB","-DUNICODE","-DWIN32","-DWIN64","-D_ENABLE_EXTENDED_ALIGNED_STORAGE","-D_UNICODE","-D_WIN64","-DQ_CREATOR_RUN","-DQT_ANNOTATE_FUNCTION(x)=__attribute__((annotate(#x)))","-IE:\\qt\\Tools\\QtCreator\\share\\qtcreator\\cplusplus\\wrappedMingwHeaders","-IE:\\qt\\Tools\\QtCreator\\share\\qtcreator\\cplusplus\\wrappedQtHeaders","-IE:\\qt\\Tools\\QtCreator\\share\\qtcreator\\cplusplus\\wrappedQtHeaders\\QtCore","-IC:\\Users\\16645\\Desktop\\McDonald\\build\\Desktop_Qt_6_7_0_MinGW_64_bit-Debug\\McDonald_autogen\\include","-IE:\\qt\\6.7.0\\mingw_64\\include\\QtCore","-IE:\\qt\\6.7.0\\mingw_64\\include","-IE:\\qt\\6.7.0\\mingw_64\\mkspecs\\win32-g++","-IE:\\qt\\6.7.0\\mingw_64\\include\\QtWidgets","-IE:\\qt\\6.7.0\\mingw_64\\include\\QtGui","-isystem","E:\\qt\\Tools\\mingw1120_64\\lib\\gcc\\x86_64-w64-mingw32\\11.2.0\\include\\c++","-isystem","E:\\qt\\Tools\\mingw1120_64\\lib\\gcc\\x86_64-w64-mingw32\\11.2.0\\include\\c++\\x86_64-w64-mingw32","-isystem","E:\\qt\\Tools\\mingw1120_64\\lib\\gcc\\x86_64-w64-mingw32\\11.2.0\\include\\c++\\backward","-isystem","E:\\qt\\Tools\\QtCreator\\bin\\clang\\lib\\clang\\17\\include","-isystem","E:\\qt\\Tools\\mingw1120_64\\x86_64-w64-mingw32\\include","-fmessage-length=0","-fdiagnostics-show-note-include-stack","-fretain-comments-from-system-headers","-fmacro-backtrace-limit=0","-ferror-limit=1000","-x","c++-header","C:\\Users\\16645\\Desktop\\McDonald\\input.h"],"directory":"C:/Users/16645/Desktop/McDonald/build/Desktop_Qt_6_7_0_MinGW_64_bit-Debug/.qtc_clangd","file":"C:/Users/16645/Desktop/McDonald/input.h"},{"arguments":["clang","-Wno-documentation-unknown-command","-Wno-unknown-warning-option","-Wno-unknown-pragmas","-nostdinc","-nostdinc++","-DQT_QML_DEBUG","-g","-std=gnu++17","-fdiagnostics-color=always","-fsyntax-only","-m64","--target=x86_64-w64-mingw32","-DMINGW_HAS_SECURE_API","-DQT_CORE_LIB","-DQT_GUI_LIB","-DQT_NEEDS_QMAIN","-DQT_WIDGETS_LIB","-DUNICODE","-DWIN32","-DWIN64","-D_ENABLE_EXTENDED_ALIGNED_STORAGE","-D_UNICODE","-D_WIN64","-DQ_CREATOR_RUN","-DQT_ANNOTATE_FUNCTION(x)=__attribute__((annotate(#x)))","-IE:\\qt\\Tools\\QtCreator\\share\\qtcreator\\cplusplus\\wrappedMingwHeaders","-IE:\\qt\\Tools\\QtCreator\\share\\qtcreator\\cplusplus\\wrappedQtHeaders","-IE:\\qt\\Tools\\QtCreator\\share\\qtcreator\\cplusplus\\wrappedQtHeaders\\QtCore","-IC:\\Users\\16645\\Desktop\\McDonald\\build\\Desktop_Qt_6_7_0_MinGW_64_bit-Debug\\McDonald_autogen\\include","-IE:\\qt\\6.7.0\\mingw_64\\include\\QtCore","-IE:\\qt\\6.7.0\\mingw_64\\include","-IE:\\qt\\6.7.0\\mingw_64\\mkspecs\\win32-g++","-IE:\\qt\\6.7.0\\mingw_64\\include\\QtWidgets","-IE:\\qt\\6.7.0\\mingw_64\\include\\QtGui","-isystem","E:\\qt\\Tools\\mingw1120_64\\lib\\gcc\\x86_64-w64-mingw32\\11.2.0\\include\\c++","-isystem","E:\\qt\\Tools\\mingw1120_64\\lib\\gcc\\x86_64-w64-mingw32\\11.2.0\\include\\c++\\x86_64-w64-mingw32","-isystem","E:\\qt\\Tools\\mingw1120_64\\lib\\gcc\\x86_64-w64-mingw32\\11.2.0\\include\\c++\\backward","-isystem","E:\\qt\\Tools\\QtCreator\\bin\\clang\\lib\\clang\\17\\include","-isystem","E:\\qt\\Tools\\mingw1120_64\\x86_64-w64-mingw32\\include","-fmessage-length=0","-fdiagnostics-show-note-include-stack","-fretain-comments-from-system-headers","-fmacro-backtrace-limit=0","-ferror-limit=1000","-x","c++-header","C:\\Users\\16645\\Desktop\\McDonald\\work.h"],"directory":"C:/Users/16645/Desktop/McDonald/build/Desktop_Qt_6_7_0_MinGW_64_bit-Debug/.qtc_clangd","file":"C:/Users/16645/Desktop/McDonald/work.h"},{"arguments":["clang","-Wno-documentation-unknown-command","-Wno-unknown-warning-option","-Wno-unknown-pragmas","-nostdinc","-nostdinc++","-DQT_QML_DEBUG","-g","-std=gnu++17","-fdiagnostics-color=always","-fsyntax-only","-m64","--target=x86_64-w64-mingw32","-DMINGW_HAS_SECURE_API","-DQT_CORE_LIB","-DQT_GUI_LIB","-DQT_NEEDS_QMAIN","-DQT_WIDGETS_LIB","-DUNICODE","-DWIN32","-DWIN64","-D_ENABLE_EXTENDED_ALIGNED_STORAGE","-D_UNICODE","-D_WIN64","-DQ_CREATOR_RUN","-DQT_ANNOTATE_FUNCTION(x)=__attribute__((annotate(#x)))","-IE:\\qt\\Tools\\QtCreator\\share\\qtcreator\\cplusplus\\wrappedMingwHeaders","-IE:\\qt\\Tools\\QtCreator\\share\\qtcreator\\cplusplus\\wrappedQtHeaders","-IE:\\qt\\Tools\\QtCreator\\share\\qtcreator\\cplusplus\\wrappedQtHeaders\\QtCore","-IC:\\Users\\16645\\Desktop\\McDonald\\build\\Desktop_Qt_6_7_0_MinGW_64_bit-Debug\\McDonald_autogen\\include","-IE:\\qt\\6.7.0\\mingw_64\\include\\QtCore","-IE:\\qt\\6.7.0\\mingw_64\\include","-IE:\\qt\\6.7.0\\mingw_64\\mkspecs\\win32-g++","-IE:\\qt\\6.7.0\\mingw_64\\include\\QtWidgets","-IE:\\qt\\6.7.0\\mingw_64\\include\\QtGui","-isystem","E:\\qt\\Tools\\mingw1120_64\\lib\\gcc\\x86_64-w64-mingw32\\11.2.0\\include\\c++","-isystem","E:\\qt\\Tools\\mingw1120_64\\lib\\gcc\\x86_64-w64-mingw32\\11.2.0\\include\\c++\\x86_64-w64-mingw32","-isystem","E:\\qt\\Tools\\mingw1120_64\\lib\\gcc\\x86_64-w64-mingw32\\11.2.0\\include\\c++\\backward","-isystem","E:\\qt\\Tools\\QtCreator\\bin\\clang\\lib\\clang\\17\\include","-isystem","E:\\qt\\Tools\\mingw1120_64\\x86_64-w64-mingw32\\include","-fmessage-length=0","-fdiagnostics-show-note-include-stack","-fretain-comments-from-system-headers","-fmacro-backtrace-limit=0","-ferror-limit=1000","-x","c++-header","C:\\Users\\16645\\Desktop\\McDonald\\order_window.h"],"directory":"C:/Users/16645/Desktop/McDonald/build/Desktop_Qt_6_7_0_MinGW_64_bit-Debug/.qtc_clangd","file":"C:/Users/16645/Desktop/McDonald/order_window.h"}]